fast_axolotl-0.1.0.dist-info/METADATA
fast_axolotl-0.1.0.dist-info/WHEEL
fast_axolotl-0.1.0.dist-info/licenses/LICENSE
fast_axolotl/__init__.py
fast_axolotl/_rust_ext.cp313-win_amd64.pyd
fast_axolotl/py.typed
fast_axolotl/streaming.py
fast_axolotl-0.1.0.dist-info/RECORD
