Metadata-Version: 2.4
Name: fast-axolotl
Version: 0.1.0
Classifier: Development Status :: 4 - Beta
Classifier: Intended Audience :: Developers
Classifier: Intended Audience :: Science/Research
Classifier: License :: OSI Approved :: MIT License
Classifier: Programming Language :: Python :: 3
Classifier: Programming Language :: Python :: 3.10
Classifier: Programming Language :: Python :: 3.11
Classifier: Programming Language :: Python :: 3.12
Classifier: Programming Language :: Rust
Classifier: Topic :: Scientific/Engineering :: Artificial Intelligence
Requires-Dist: datasets>=2.14.0
Requires-Dist: numpy>=1.24.0
Requires-Dist: pytest>=7.0 ; extra == 'dev'
Requires-Dist: pytest-cov>=4.0 ; extra == 'dev'
Requires-Dist: ruff>=0.1.0 ; extra == 'dev'
Provides-Extra: dev
License-File: LICENSE
Summary: High-performance Rust extensions for Axolotl - drop-in acceleration for existing installations
Keywords: axolotl,llm,training,rust,performance
License-Expression: MIT
Requires-Python: >=3.10
Project-URL: Homepage, https://github.com/axolotl-ai-cloud/fast-axolotl
Project-URL: Repository, https://github.com/axolotl-ai-cloud/fast-axolotl.git
